Verilog/cmos_inverter.v
module cmos_inverter (inv_out, inv_in);
	output inv_out;
	input inv_in;
	supply0 GND;
	supply1 PWR;

	pmos(inv_out, PWR, inv_in);
	nmos(inv_out, GND, inv_in);
endmodule

Verilog/tx_gate.v
`include "cmos_inverter.v"
module tx_gate (out, sel, in);
	output out;
	input sel, in;
	wire sel_bar;

	pmos(out, in, sel_bar);
	nmos(out, in, sel);
	cmos_inverter inv (sel_bar, sel);
	pulldown (out);
endmodule

Verilog/tb_tx_gate.v
`timescale 1ns/ 1ps
module tb_tx_gate;
	reg sel, in;
	wire out;

	tx_gate uut(
		.out(out),
		.sel(sel),
		.in(in)
	);

	$dumpfile("tb_tx_gate.vcd");
	$dumpvars(0, tb_tx_gate);
	in = 1;
	sel = 0;
	#20 $finish;
	end

always #2 sel = ~sel;
always #1 in = $random;
endmodule

Verilog/tb_tx_gate.vcd
$date
	Tue Aug 03 17:12:09 2021
$end
$version
	Icarus Verilog
$end
$timescale
	1ns
$end
$scope module tb_tx_gate $end
$var wire 1 ! out $end
$var reg 1 " in $end
$var reg 1 # sel $end
$scope module uut $end
$var wire 1 " in $end
$var wire 1 ! out $end
$var wire 1 # sel $end
$var wire 1 $ sel_bar $end
$scope module inv $end
$var wire 1 % GND $end
$var wire 1 & PWR $end
$var wire 1 # inv_in $end
$var wire 1 $ inv_out $end
$upscope $end
$upscope $end
$upscope $end
$enddefinitions $end
#0
$dumpvars
1&
0%
1$
0#
1"
0!
$end
#1
0"
#2
1"
1!
0$
1#
#3
0!
0"
#4
1"
0!
1$
0#
#5
0"
#6
1"
1!
0$
1#
#7
0!
0"
#8
1"
0!
1$
0#
#9
0"
#10
1"
1!
0$
1#
#11
0!
0"
#12
1"
0!
1$
0#
#13
0"
#14
1"
1!
0$
1#
#15
0!
0"
#16
1"
0!
1$
0#
#17
0"
#18
1"
1!
0$
1#
#19
0!
0"
#20
1"
0!
1$
0#
